{
"meta":{"test_sets":[],"test_metrics":[],"learn_metrics":[{"best_value":"Min","name":"RMSE"}],"launch_mode":"Train","parameters":"","iteration_count":100,"learn_sets":["learn"],"name":"experiment"},
"iterations":[
{"learn":[13.88550808],"iteration":0,"passed_time":0.001209028635,"remaining_time":0.1196938349},
{"learn":[12.9948338],"iteration":1,"passed_time":0.002361175412,"remaining_time":0.1156975952},
{"learn":[12.15807038],"iteration":2,"passed_time":0.003410232632,"remaining_time":0.1102641884},
{"learn":[11.41610927],"iteration":3,"passed_time":0.004432033549,"remaining_time":0.1063688052},
{"learn":[10.74886278],"iteration":4,"passed_time":0.006006861451,"remaining_time":0.1141303676},
{"learn":[10.25754577],"iteration":5,"passed_time":0.007291256395,"remaining_time":0.1142296835},
{"learn":[9.721805013],"iteration":6,"passed_time":0.008345836866,"remaining_time":0.1108804041},
{"learn":[9.25572477],"iteration":7,"passed_time":0.009269865411,"remaining_time":0.1066034522},
{"learn":[8.866181283],"iteration":8,"passed_time":0.01033223588,"remaining_time":0.104470385},
{"learn":[8.469328019],"iteration":9,"passed_time":0.01144894478,"remaining_time":0.103040503},
{"learn":[8.094183793],"iteration":10,"passed_time":0.01247295816,"remaining_time":0.1009175705},
{"learn":[7.789035615],"iteration":11,"passed_time":0.01353677532,"remaining_time":0.09926968567},
{"learn":[7.54670764],"iteration":12,"passed_time":0.01460470857,"remaining_time":0.0977392035},
{"learn":[7.287960671],"iteration":13,"passed_time":0.01567053872,"remaining_time":0.09626188068},
{"learn":[7.05972283],"iteration":14,"passed_time":0.017713579,"remaining_time":0.1003769477},
{"learn":[6.884652858],"iteration":15,"passed_time":0.01884908856,"remaining_time":0.09895771495},
{"learn":[6.708971864],"iteration":16,"passed_time":0.01994913494,"remaining_time":0.09739871765},
{"learn":[6.546616659],"iteration":17,"passed_time":0.02137333431,"remaining_time":0.09736741187},
{"learn":[6.401707162],"iteration":18,"passed_time":0.02255767406,"remaining_time":0.09616692627},
{"learn":[6.292906488],"iteration":19,"passed_time":0.023673672,"remaining_time":0.09469468798},
{"learn":[6.191078005],"iteration":20,"passed_time":0.02470861567,"remaining_time":0.09295145895},
{"learn":[6.100668748],"iteration":21,"passed_time":0.02589641062,"remaining_time":0.09181454673},
{"learn":[6.000090012],"iteration":22,"passed_time":0.02694278922,"remaining_time":0.09019977259},
{"learn":[5.917705427],"iteration":23,"passed_time":0.02795529705,"remaining_time":0.08852510732},
{"learn":[5.84457307],"iteration":24,"passed_time":0.02893532152,"remaining_time":0.08680596456},
{"learn":[5.788070708],"iteration":25,"passed_time":0.03049089367,"remaining_time":0.08678177428},
{"learn":[5.725270492],"iteration":26,"passed_time":0.03204397218,"remaining_time":0.08663740626},
{"learn":[5.664077595],"iteration":27,"passed_time":0.03388158015,"remaining_time":0.08712406324},
{"learn":[5.616119031],"iteration":28,"passed_time":0.03504828634,"remaining_time":0.08580787344},
{"learn":[5.570559179],"iteration":29,"passed_time":0.03620344719,"remaining_time":0.0844747101},
{"learn":[5.525254852],"iteration":30,"passed_time":0.03765391732,"remaining_time":0.0838103321},
{"learn":[5.485942286],"iteration":31,"passed_time":0.0388471591,"remaining_time":0.08255021308},
{"learn":[5.450631822],"iteration":32,"passed_time":0.03987150319,"remaining_time":0.08095123374},
{"learn":[5.422421023],"iteration":33,"passed_time":0.04151771807,"remaining_time":0.08059321744},
{"learn":[5.388379799],"iteration":34,"passed_time":0.0428904927,"remaining_time":0.07965377215},
{"learn":[5.355387569],"iteration":35,"passed_time":0.04408156233,"remaining_time":0.07836722192},
{"learn":[5.328437293],"iteration":36,"passed_time":0.04545237957,"remaining_time":0.07739188955},
{"learn":[5.306903618],"iteration":37,"passed_time":0.04668904503,"remaining_time":0.07617686294},
{"learn":[5.285433404],"iteration":38,"passed_time":0.05109285597,"remaining_time":0.07991446703},
{"learn":[5.267101362],"iteration":39,"passed_time":0.05260014234,"remaining_time":0.07890021352},
{"learn":[5.251095649],"iteration":40,"passed_time":0.05423010501,"remaining_time":0.07803844379},
{"learn":[5.237584004],"iteration":41,"passed_time":0.05536695111,"remaining_time":0.07645912296},
{"learn":[5.217408918],"iteration":42,"passed_time":0.05661068163,"remaining_time":0.07504206635},
{"learn":[5.206995408],"iteration":43,"passed_time":0.05791287115,"remaining_time":0.07370729055},
{"learn":[5.193572681],"iteration":44,"passed_time":0.06054440687,"remaining_time":0.07399871951},
{"learn":[5.171953246],"iteration":45,"passed_time":0.06216313409,"remaining_time":0.07297411393},
{"learn":[5.156819442],"iteration":46,"passed_time":0.0637140199,"remaining_time":0.07184772457},
{"learn":[5.138035206],"iteration":47,"passed_time":0.06496657261,"remaining_time":0.07038045366},
{"learn":[5.123789848],"iteration":48,"passed_time":0.06626633885,"remaining_time":0.06897108738},
{"learn":[5.10348292],"iteration":49,"passed_time":0.06814090149,"remaining_time":0.06814090149},
{"learn":[5.092919557],"iteration":50,"passed_time":0.07036159208,"remaining_time":0.06760231396},
{"learn":[5.074086188],"iteration":51,"passed_time":0.07167012016,"remaining_time":0.06615703399},
{"learn":[5.061655743],"iteration":52,"passed_time":0.07343855519,"remaining_time":0.06512475649},
{"learn":[5.039548991],"iteration":53,"passed_time":0.07449660482,"remaining_time":0.06346007077},
{"learn":[5.036718343],"iteration":54,"passed_time":0.07508807849,"remaining_time":0.06143570059},
{"learn":[5.021933856],"iteration":55,"passed_time":0.07615381852,"remaining_time":0.05983514312},
{"learn":[5.015169804],"iteration":56,"passed_time":0.07723748276,"remaining_time":0.05826687296},
{"learn":[4.994686175],"iteration":57,"passed_time":0.07871753313,"remaining_time":0.05700235157},
{"learn":[4.98355802],"iteration":58,"passed_time":0.07997396081,"remaining_time":0.05557512531},
{"learn":[4.969852264],"iteration":59,"passed_time":0.08096104429,"remaining_time":0.05397402953},
{"learn":[4.959291045],"iteration":60,"passed_time":0.08209681894,"remaining_time":0.05248813014},
{"learn":[4.944132475],"iteration":61,"passed_time":0.08317795003,"remaining_time":0.05098003389},
{"learn":[4.936412547],"iteration":62,"passed_time":0.08437751087,"remaining_time":0.04955504607},
{"learn":[4.925435618],"iteration":63,"passed_time":0.08560886915,"remaining_time":0.0481549889},
{"learn":[4.920717592],"iteration":64,"passed_time":0.0869647715,"remaining_time":0.04682718466},
{"learn":[4.908644991],"iteration":65,"passed_time":0.08829223517,"remaining_time":0.04548387872},
{"learn":[4.899357564],"iteration":66,"passed_time":0.08983979623,"remaining_time":0.04424945187},
{"learn":[4.887030902],"iteration":67,"passed_time":0.09093692841,"remaining_time":0.04279384866},
{"learn":[4.875666687],"iteration":68,"passed_time":0.0919271116,"remaining_time":0.04130058637},
{"learn":[4.863171197],"iteration":69,"passed_time":0.0930625508,"remaining_time":0.03988395034},
{"learn":[4.853253942],"iteration":70,"passed_time":0.0942512164,"remaining_time":0.03849697571},
{"learn":[4.84513027],"iteration":71,"passed_time":0.09533351933,"remaining_time":0.0370741464},
{"learn":[4.833654152],"iteration":72,"passed_time":0.09634710862,"remaining_time":0.03563523196},
{"learn":[4.823714406],"iteration":73,"passed_time":0.09741418572,"remaining_time":0.03422660579},
{"learn":[4.817732191],"iteration":74,"passed_time":0.09843079936,"remaining_time":0.03281026645},
{"learn":[4.808628768],"iteration":75,"passed_time":0.09972204883,"remaining_time":0.03149117331},
{"learn":[4.799041713],"iteration":76,"passed_time":0.100844691,"remaining_time":0.03012244017},
{"learn":[4.797532726],"iteration":77,"passed_time":0.1015386434,"remaining_time":0.02863910455},
{"learn":[4.785437472],"iteration":78,"passed_time":0.1026755048,"remaining_time":0.02729348862},
{"learn":[4.778245253],"iteration":79,"passed_time":0.1035950272,"remaining_time":0.02589875681},
{"learn":[4.773870799],"iteration":80,"passed_time":0.1044706248,"remaining_time":0.02450545521},
{"learn":[4.765987613],"iteration":81,"passed_time":0.105961645,"remaining_time":0.0232598733},
{"learn":[4.760827165],"iteration":82,"passed_time":0.1069328473,"remaining_time":0.02190190848},
{"learn":[4.751082412],"iteration":83,"passed_time":0.1078967645,"remaining_time":0.02055176466},
{"learn":[4.747591244],"iteration":84,"passed_time":0.1089123668,"remaining_time":0.01921982943},
{"learn":[4.745843976],"iteration":85,"passed_time":0.1109777427,"remaining_time":0.01806614417},
{"learn":[4.733820276],"iteration":86,"passed_time":0.1123901662,"remaining_time":0.01679393288},
{"learn":[4.716522221],"iteration":87,"passed_time":0.1134649479,"remaining_time":0.0154724929},
{"learn":[4.705154128],"iteration":88,"passed_time":0.1145078526,"remaining_time":0.01415265594},
{"learn":[4.704120683],"iteration":89,"passed_time":0.1157384154,"remaining_time":0.01285982393},
{"learn":[4.694937858],"iteration":90,"passed_time":0.1166859957,"remaining_time":0.0115403732},
{"learn":[4.683298107],"iteration":91,"passed_time":0.1175930213,"remaining_time":0.01022548011},
{"learn":[4.675841972],"iteration":92,"passed_time":0.1185949751,"remaining_time":0.008926503504},
{"learn":[4.665476304],"iteration":93,"passed_time":0.1197635541,"remaining_time":0.007644482177},
{"learn":[4.658359397],"iteration":94,"passed_time":0.1212014119,"remaining_time":0.006379021681},
{"learn":[4.653286038],"iteration":95,"passed_time":0.1225555414,"remaining_time":0.00510648089},
{"learn":[4.641688371],"iteration":96,"passed_time":0.123610407,"remaining_time":0.003823002277},
{"learn":[4.640772665],"iteration":97,"passed_time":0.1245996689,"remaining_time":0.002542850386},
{"learn":[4.624096714],"iteration":98,"passed_time":0.1256135133,"remaining_time":0.001268823367},
{"learn":[4.617338508],"iteration":99,"passed_time":0.1267382132,"remaining_time":0}
]}